<?xml version="1.0" encoding="UTF-8" standalone="no"?>
<pk><wd nm="bycategory" rd="59,0:11627|154,0:779,2033,3215|158,0:1782,2767,3954,4383,5084,5511|162,0:4375,5657"/><wd nm="bye" rd="132,0:1542"/><wd nm="byid" rd="168,0:12911|173,0:11131|186,0:2434"/><wd nm="bypass" rd="132,0:3066|143,0:1834|172,0:2075"/><wd nm="bypassed" rd="172,0:2117"/><wd nm="bypercent" rd="59,0:1484,2599,38313|156,0:564,909,3213,3413,5529,5892,6997,8320,9361|157,0:1804,3006,4023|161,0:445"/><wd nm="byte" rd="6,0:4258|9,0:951,1238,2875,2998,3533,3541,3552,3563|31,0:4258|78,0:7295,7576|115,0:5754,5931|132,0:1640"/><wd nm="bytes" rd="6,0:4181,4267,4445,4554|9,0:721,983,2697|31,0:4181,4267,4445,4554|78,0:6935,7327"/><wd nm="c" rd="0,0:399,3638|1,0:167,1989|2,0:108|4,0:1399,7080,7176,7321|6,0:107,183,218,1451,3274|7,0:695,1110,1563,1868,2447|8,0:1427|9,0:182,762,1432,1492,2031,2254,2797,4132|10,0:109,706,1306,1904,2513,2891,2937,2963,3389,3408,3431,3505|11,0:5327|14,0:876,2691|15,0:2226,2600|16,0:849,2270|17,0:546|21,0:167,855,3062,3549,3588,5842,6881,8298|22,0:1854,1975,2092,2553,3953|23,0:142,497,1894,1933,2806,5417|24,0:702|25,0:249,296,355,431,1514,1614,1627,1887,10097,10442,24719,25213,27095|26,0:102,300,2375,3557,3997,4100,4224|27,0:101|28,0:1180,2116,2712|29,0:1313,1606,1954|30,0:1399,7080,7176,7320|31,0:107,183,218,1451,3274,6415|33,0:2419,3428,3877,4765|34,0:318|37,0:418,695,1406,1699,2173,2462,2974,3280,5296,5739|38,0:333|46,0:405,991|49,0:669,723,875,897,5788,5809,10238,10539,10716,11484|50,0:2488,5404,8890,15363,15691,18809,19082,19174,19572,20385,20604,23214,24590,31909,32096,32223,32362,40093,40269,42067,49360,55956,56085,56223|51,0:595,615,2618,2639,8823,10958,10993,11043,11203,11253,14051,15071,15418,18515,18607,19005,23378,33345,33532,33659,33798,39145,39195,40757,42612,43606,44666,44795,44933,46418,46555,46693|52,0:4603,7555,10581,17373,17701,18232,21092,21184,21582,25628,27018,34065,34252,34379,34518,42003,42190,43992,48314,48398,48484,48564,48641,48707,48778,49126,49894,50167,50975,51786,51924|53,0:4157,6837,9831,16289,16617,17148,20008,20100,20498,22514,23794,30832,31019,31146,31285,39041,39195,40995,43998,44782,46436,47697,47835|54,0:4533,7484,11021,17808,18136,18667,21527,21619,22017,25294,26574,33612,33799,33926,34065,41482,41636,43433,48760,48874,50153,50444,50524,50601,50667,50738,50823,50909,51504,52553,52691|55,0:8835,11538,11721,11904,11947,12107,12150,13840,15585,15913,16451,19342,19434,19832,20581,21766,27670,27857,27984,28123,33338,34236,34279,35471,38257,38438,38535,38714,44035,44164,44302,44531,46113,46249,46387,46616|56,0:708,735,1609,1628,5661,10219,11278,12164,12492,15588,15680,16087,16377,18335,19616,26661,26848,26972,27111,34609,34763,36561,38948,39585,39947,40992,42252,42390|57,0:608,1408,3259,6308,10711,13051,13379,16495,16768,16860,17267,20953,22341,29410,29597,29724,29863,37104,37279,39077,42821,43164,44538,44609,44694,44780,44860,44937,45006,45183,45787,45916,46054|58,0:604,2143,4629,7879,12653,12703,12863,12913,13998,15936,16197,16721,17049,20165,20438,20530,20928,21206,21299,26314,27606,28062,29846,44291,44478,44602,44741,51546,51596,52371,57470,57582,57915,58132,58227,58371,58485,59677,59806,59944,61774,61911,62049|59,0:3987,6690,8199,11834,12625,12953,16071,16344,16436,16834,17344,17919,18047,18171,24737,26748,26827,27020,27190,27285,32510,32697,32824,32963,36173,36956,38095,38149,38438,38800,38976,39109,39168,39289|60,0:913,1991,2837,4048,6999,11548,13005,13333,13864,16722,16814,17212,17675,18250,18378,21415,22719,29751,29938,30062,30201,37702,37877,39675,42906,42954,43038,43124,43204,43281,43347,43418,43766,44531,45440,46251,46389|61,0:929,2008,2862,3802,6480,10150,12439,12767,13298,16157,16249,16647,17440,17659,18247,18375,18499,19492,20794,27772,27959,28086,28225,36029,36207,38005,40525,40671,41340,42382,43641,43779|62,0:923,2001,2851,4068,7020,12760,13528,13856,14387,17245,17337,17735,21228,22532,29573,29760,29884,30023,37527,37701,39499,43700,43814,45102,45393,45473,45550,45616,45687,45772,45858,46453,47502,47640|63,0:294,3500,6205,9640,11860,13762,14090,17208,17480,17572,17970,20895,27232,27419,27543,27682,33382,33441,33600,33756,33904,34065,34220,34385,34833,35648,36150,36297,37573,38376,38514|64,128:0,42,438,475,520,911,1938,3487,5524,5587,5627,6277,11595,11923,12454,15314,15406,15804,16642,16861,17436,17564,17688,19621,19865,26903,27090,27217,27356,35159,35202,35333,37131,38721,39780,39894,40662,41455,41584,41722,43622|65,128:0,38,434,467,508,895,1922,3748,6050,6113,6153,6803,12677,13005,13536,16394,16486,16884,21530,28571,28758,28882,29021,34615,35121,36522,36565,36696,38494,41803,42679,42793,44084,44371,44442,44527,44613,44693,44770,44839,45434,45563,45701,47601|66,0:3577,6154,10357,11816,12105,12636,15564,15656,16054,19453,20239,27286,27473,27597,27736,34782,34959,36767,36830,37978,38761,43343,47557,47671,48959,49249,49329,49406,49472,49543,49628,49714|67,0:919,1946,3762,6715,10721,13010,13338,13869,16732,16824,17222,20447,21754,28793,28980,29104,29243,36746,36927,38725,42620,42734,44111,44182,44267,44353,44433,44510,44579,45174,45302,45440|68,0:943,1970,3789,6739,10236,12524,12852,13383,16240,16332,16730,17240,17512,17640,20676,21993,29032,29219,29343,29482,36984,37159,38957,43035,43149,44524,44595,44680,44766,44846,44923,44992,45586,45714,45852|69,0:924,1685,3279,6206,10399,12914,13242,13773,16645,16737,17135,20537,21926,28986,29173,29297,29436,36859,37034,38835,42603,42947,44325,44396,44481,44567,44647,44724,44793,44970,45575,45703,45841|70,0:652,712,1628,2380,2440,3198,5707,8039,10599,10691,11089,16487,16674,16798,16937,19152,19228|71,0:2691,4190,6486,8445,8695,11255,11347,11745,15051,15549,22589,22776,22900,23039,28483,31952,32066,32921,32992,33077,33163,33243,33320,33389|72,0:5019,8048,11128,11174,11334,11380,13078,15016,15277,16829,17157,17688,20548,20640,21038,21336,21439,25391,26683,27406,29174,37420,37607,37734,37873,44621,44675,45450,48818,48928,49141,49919,50483,50612,50750,52513,52650,52788|73,0:872,1535,2951,5787,9741,12029,12357,15475,15747,15839,16237,18586,25254,25441,25565,25704,31658,31772,33205,33366,33521,33686,33845,34001,34149,34631,34806,36854,36983,37121|74,0:899,1562,2993,5831,9265,11554,11882,15000,15273,15365,15763,16333,16605,16733,16857,19102,25770,25957,26082,26221,32463,32577,34010,34171,34326,34491,34650,34806,34954,35436,35621,37651,37779,37917|75,0:2138,4695,8335,10817,11145,14262,14535,14627,15025,15807,16382,16510,16634,18110,24055,24242,24369,24508,31001,31469,32293,32858,33023,35071,35200,35338|76,0:549,1057,1675,1883,2029|77,0:940,1183,1368,1608,1918|78,0:1534,1702,1861,3428,7132|79,128:0,22,245,575,958,975,1271,1390,1399,2789,2808,3982,4045,4421|80,0:380,3290|81,0:3968,5080,6148|83,0:4021,5218,5550|84,0:213,350|85,0:325,660|86,0:305|88,0:5235,5571|89,0:284,4033,4369|91,0:176,818,1466|93,0:2009,2078|94,0:836,1756,1893,2616,2932,3582,4481|95,0:363,1627,1721,2423,2917,2954,3162,4987,7138,7526,7579,12828,15957,23323,24102,29408,30188,35484,36262,41561,42340,48435,49249,54806,55621,61168,61981,67531,68345,72452|97,0:2251|98,0:119,484,2434|99,0:1330|100,0:283,766,1751,1892|101,0:118,258,528,619,713|103,0:119,259,529,620,707|104,0:355,977|105,0:122,262,1259,1374,1477,1600,1719,1826,1945,2067,2177|106,0:455,1496,3404,3481|107,0:593,1145,1172,2089,2108,4620,5845|108,0:1745,1804|111,0:2867,2926,4988,5968,6027,9504,10059|112,0:1536,1595|113,0:2819,2878,5741,5800,7897,8231|115,0:1104,1163,2850,2909,6272,7000|119,0:2896|120,0:1271,1312|121,0:966,1758|122,0:2734|123,0:267,5294|126,0:3233,7695|131,0:1631,1794,2072,2912,5809,5909,5957,5978,6033,9836,10305,11772|132,0:5822,8961|133,0:836|134,0:380|135,0:437|137,0:1091,1471,2571,2895,4089|138,0:938|139,0:953,1634,2522,2968,3280,4005,4155|140,0:227,510,1055,1719,1820,2064|141,0:968|142,0:191,574,853|143,0:4188|144,0:657,674,1657,2017,2846,3468,5036,5791,6248,6267,6319,7242,7844,7944,9040,9291,9879,10624,10643|145,0:780,1163,1839,2410,3343,3683,4441,5436,5453,5817,6562,6581|146,0:729,1450,2035,3926,6499,7274|147,0:639,1692|148,0:813,1645,2374,7522,7624|149,0:896,962,1013,1060,1109,1152,2041,2363,3556,3599,3659,3688,3741,3762,3988,4037,4086,4148,4198,4262,4316,4382,4429,4733,4815,4850,4880,4917,4948,4979,6104,6139,6169,6206,6237,6268,6527|150,0:880,1244,3006|151,0:144,232,288,335,643,1260,1289,1529,1684,1961|152,0:465,1115,1173,1228,1715,1734,1858,1877,2596,2654,2709,3356,5387,10962|153,0:1037,1823,2749,2766,3430,4202,5173|154,0:133,179,443,456,541,673,817,1931,2075,3884|155,0:307,2530,2873,3074,3112|156,0:179,1153,1381,1550,1639,1945,2085,2217,2335,2478,2807,2889,3695,3944,4216,4257,5246,6148|157,0:87,1085,1148,1227,1311,1584|158,0:290,309,459,485,711,829,946,1062,1534,1676,2053,2665,3013,3891,3941,3980,4301,4348,4369,4956,5109,5159,5409,5534,5581|159,0:52,556,661,764|160,128:12,33,54,94,120,219,390,432,1308,1352,1396,1440,1484,2636,2675,2714,2753,2792,3210,3418,3708,4040,4491,5267,5311,5355,5399,5443,6058,6733,6772,6811,6850,6889,8736,10000,10036,10405,12486,12643|161,0:79,165|162,0:199,721,735,992,1211,1984,2028,2072,2116,2160,2775,3450,3489,3528,3567,3606,4052,4108,4269,4413,5555,5746|163,0:333,351,407|164,0:379,396,648,728,745,1706|165,0:1393|166,0:367,1154,1171,1950,1968,2024|167,0:94|168,0:153,1849,1866,2334,2534,3250,3303,3322,4144,4768,6098,6317,6600,7717,9006,9534,10039,13095,14754,14994,15052,15107,15457,15476,15576,15595,15753,18535,19433,20984,32290,32508,32731,33587,33827|170,0:429,4200,4705,4771,4980,6097,6301,6383,7104,7297,7354,7618,8195,8717,8774,9226,9672,9783,9969,10302,10360,10576,10751,10806,11633|171,0:465|172,0:650,1108,2152,2189,3472,4160|173,0:715,1043,1260,2412,4942,5803,14963,19228,21048,21581,22844,24177,25169,25580,27683|174,0:1246,1938,2393|175,0:344,787,1349,1404,1586,1978,3737,3881,3913|176,0:588,1978|177,0:726,2490,6090|178,0:435,1464,1815,2992|179,0:367,433,444,1222,1482,1857,1874,3844|180,0:1530,4917,5182,5550,6898,7183|181,0:2972,3056,3140,5664|182,0:327,1580,2863,3783,4929,5043,5493|183,0:2370,3091,5291,6832,6904,8034,8106,9518,11020,12537|184,0:361,1627,1721,2242,3025,3062,3270,5089,7186,7570,7622,13011,16097,16164,17308,17418,17485,18578,18645,18769,19985,20095,20162,20334,21593,21660,21832,21980,23461,23523,23683,25229,25389,25510,27305,27445,27512,27578,29001,29068,29192|185,0:578,646,1916,3241,3258|186,0:299,1992,3061|187,0:1034,1419,1477,1532,3927,11133|188,0:2791,6614,7690|189,0:1359|190,0:467,1446,1465,1625,1680,1738,1862,1881,2649,2707,2762,3325,5358,9497,9696|191,0:635,1151,4185|195,0:129|196,128:0,27,49,143,242,262,322,537,574,1088,1717,1911,2444,3099,3337,3395,3440,3661,3809,3942,4099,4393|197,0:426,585,1702,3056|199,0:375,479,524,565,3059|201,0:639,950,1010,1926,2676,2740,3574|202,0:74,955,1095,1591|203,0:193,1109|204,0:371|206,0:3169,5224|209,0:207,302,532,2194,2457,5627,8144,9222,9302,9316|212,0:653,1189,1255,1291,2354,2529,2629,2723,2730,2752,2762|214,0:448,906,2533,4132,5843|215,0:439|216,0:262,492,863,1217,1801,1995,2090,2184|217,0:1944,2042,2237,2372|220,0:320,416,466,624,671,761,1470,1487,2167,2735,2844|221,0:472,504,1235,1508,1525,2105,2669,2783|222,0:403,889,926"/></pk>