<?xml version="1.0" encoding="UTF-8" standalone="no"?>
<pk><wd nm="kedcharts" rd="95,0:8,30,44,772,890,1921,2297,2382,2549,2772,2815,2895,3551,3712,7758,9376,12032,12106,12157,12358,14408,15166,15333,15913,68828,68907,70016,70096,72328,72371,72399|96,0:0,28,79,149,469,772,824,871,3029,4131,4224,4290,4377|97,0:0,27,77,147,466,782,834,872,4004,4158,4245|98,0:2255,2334|100,0:646,680,1255|142,0:454,488,2704|146,0:7237|148,0:8,30,97,695,1088,2115,2534,6806,7795,7856,7904,8155,8219,8279|168,0:7802,8971|170,0:1497,1971,4847,5360|173,0:17681,17800,17829|174,0:645|182,0:586|184,0:8,30,44,769,887,1921,2191,2359,2465,2901,3658,3819,7803,9307,9542,12217,12291,12342,12543,14490,14845,14932,15228,15472,17054,17097,17701,17828,18964,19172,19239,19820,21210,22646,23240,23296,26375,27146,28181,29511,30057|185,0:889,3586"/><wd nm="keddata" rd="95,0:8895,9110,9845,10060,10070,10283,10293,10507,10517,10732,11053,16198,18425,18739,19026,19395,19405,19774,19784,20150,20167,20177,20457,20824,20834,21198,21208,21573,21590,21600,21887,22253,22263,22631,22641,23012,23029,23039,23331,23699,23709,24079,24089,24459,24476,24493,24503,24817,25106,25475,25485,25855,25865,26232,26249,26259,26541,26907,26917,27281,27291,27656,27673,27683,27971,28337,28347,28715,28725,29096,29113,29123,29416,29785,29795,30165,30175,30545,30562,30579,30589,30903,31189,31558,31568,31938,31948,32314,32331,32341,32622,32989,32999,33362,33372,33738,33755,33765,34051,34417,34427,34794,34804,35174,35191,35201,35492,35860,35870,36239,36249,36619,36636,36653,36663,36977,37264,37633,37643,38012,38022,38388,38405,38415,38695,39062,39072,39436,39446,39811,39828,39838,40125,40491,40501,40869,40879,41250,41267,41277,41569,41937,41947,42317,42327,42697,42714,42731,43270,43620,43942,45439,46935,48445,49984,50308,51809,53305,54816,56356,56677,58176,59671,61178,62716,63038,64535,66031,67541,69129,69279,69543,69573,69834,69864,70323,70475,70505,70525,70839,70869,71135,71165|96,0:1270,2924,3142,3266,3554,3741,3846|97,0:1230,1443,1453,1666,1676,1889,1899,2112,2208,2952,3167,3309,3522,3586|148,0:2864,3082,3092,3308,3318,3535,3545,3763,4080,5599,5730,5747,5897,6594,6745,6768,6963|184,0:8946,9164,10011,10229,10239,10455,10465,10682,10692,10910,11228"/><wd nm="keditemclose" rd="172,0:13233|174,0:2964"/><wd nm="keditemclosed" rd="172,0:13589|174,0:2986|184,0:15855,16709"/><wd nm="keditemopen" rd="172,0:12591|174,0:2926|184,0:15637,18204,19626,19754,21136,23033,23166,24776,26762,26960,28635,30444,30571"/><wd nm="keditemopened" rd="172,0:12884|174,0:2947|184,0:15712,16583"/><wd nm="keep" rd="70,0:1135,1791,2796,3353|78,0:4529,8213|145,0:3997|148,0:2291|149,0:757,3501|153,0:2873|170,0:8330|183,0:9612|201,0:1433,2089,3135,3740|209,0:6352"/><wd nm="keeping" rd="145,0:2754|149,0:3379,3433|165,0:2305"/><wd nm="keeps" rd="95,0:14153,72193"/><wd nm="kely" rd="78,0:4735|124,0:4074|141,0:2019"/><wd nm="ken" rd="6,0:2278|8,0:476,1780|22,0:2351,2390|31,0:2278,5461,6768|52,0:8634|54,0:8563|57,0:7401|60,0:8092|62,0:8104|65,0:7895|66,0:7246|69,0:7299|78,0:7972|132,0:4728|156,0:2903|168,0:6057,31543,33085|208,0:1772"/><wd nm="kept" rd="100,0:758|141,0:1587|142,0:566|165,0:2551|173,0:6991"/><wd nm="ker" rd="34,0:441|39,128:6,5357,5402,5565,5642,5723,5793,5870,5951,6182|40,128:6,56,1716,2034|41,128:6,50,229,472,3774,4947|42,128:6,42,1649|43,128:6,5626|44,128:6,6183|45,128:6,4273|46,128:6,34,54,323,431,1002,1983,2228,2369|47,128:6,6158|48,128:6,6133|50,128:6,42,434,505,22260,22337,22418,22493,22570,22644,24351,40142,44258,44335,44416,44491,44568,44642,48739,48889,51442,51519,51600,51675,51752,51826,58126|51,0:4819,20564|52,0:3554,23134|54,0:3478,22722|57,0:2204,18460|58,0:3574|60,0:2999,18916|62,0:3013,18644|63,0:2445,18732|65,0:2693,17846|66,0:2468,16963|67,0:2713,17868|68,0:2741,18184|69,0:2230,18044|71,0:1806,13295|72,0:3964|73,0:1907,16746|74,0:1938,17351|86,0:918|87,0:972,1118,1242,1357|163,0:1240|166,0:2861|170,0:3406,5144|211,0:397|213,0:1084|214,0:4799|215,0:1245"/><wd nm="ker2d" rd="50,0:77|163,0:1263,1279|166,0:2884,2900"/><wd nm="keralpha" rd="39,0:5663,5891|50,0:22345,22578,44343,44576,51527,51760"/><wd nm="kercircle" rd="51,0:25225|52,0:29051|53,0:25827|54,0:28607|55,0:23862|56,0:21652|60,0:24755|61,0:22830|62,0:24568|64,0:21898|65,0:23566|66,0:22273|67,0:23790|68,0:24028|71,0:17585|72,0:31207|168,0:20635"/><wd nm="kercolor" rd="39,0:5516,5744|50,0:22193,22426,44191,44424,51375,51608"/><wd nm="kers" rd="39,0:320,5290,5441,6022|50,0:465,14308|52,0:639,2177|54,0:639,2101|98,0:1057"/><wd nm="kerslimitswidthratio" rd="39,0:5972|50,0:14222"/><wd nm="kerthickness" rd="39,0:5586,5814|50,0:22268,22501,44266,44499,51450,51683"/><wd nm="kes" rd="4,0:4272|7,0:2390|8,0:1607|25,0:2307,5385|30,0:4272|31,0:6595|50,0:56616|51,0:45327,47086|52,0:52318|53,0:47036|54,0:53084|55,0:44707,46792|56,0:41591|57,0:46447|58,0:60337,62441|59,0:11574|60,0:46783|61,0:42980|62,0:48033|63,0:38907|64,0:42115|65,0:46094|67,0:45833|68,0:46245|69,0:46234|71,0:12933,12944,13057,13068,13170,13181|72,0:51143,53181|73,0:37514|74,0:38310|75,0:35732|80,0:100,2173,3738|81,0:580|83,0:5212,5544|86,0:1432|94,0:2452|95,0:1340,3489|98,0:2317|100,0:1817|111,0:5650|115,0:5070|119,0:3728|121,0:1232,1870,1900|131,0:9619,9841|132,0:594|133,0:1725|139,0:3789|140,0:1220|141,0:411,2640|144,0:9352|146,0:5200|147,0:3288|148,0:5252,6013,6262,7120,8020|152,0:256,3451|153,0:340,2989|168,0:23120,24321,32912,36235|171,0:401|172,0:116|173,0:122,10450,13210,13800,14602,14879,16845,21726,21974,25163,25574|174,0:130|175,0:124|176,0:98,4646|177,0:110,3305,3330,3679,3752|178,0:94|179,0:118,3785|180,0:100,1031,4085|181,0:144|182,0:86,2015|183,0:11010,13592|184,0:3596|185,0:120|186,0:116,3797,4094,4491|187,0:167,1947,8935|188,0:124,5542,10117|189,0:135|190,0:241,3424|192,0:116|202,0:1311|222,0:742"/><wd nm="kest" rd="156,0:3572"/><wd nm="ket" rd="162,0:242"/><wd nm="kethickness" rd="71,0:13004"/><wd nm="keting" rd="70,0:1814,1834,3368,3387|201,0:2112,2132,3758,3778|204,0:787,1667"/><wd nm="kets" rd="11,0:2147|12,0:104|25,0:27002|76,0:1298"/><wd nm="kewise" rd="76,0:4165"/><wd nm="key" rd="46,0:513|50,0:26431,26510|52,0:28623,28702|53,0:25399,25478|54,0:28179,28258|55,0:23434,23513|56,0:21224,21303|57,0:23929,24008|58,0:31433,31512|59,0:26321,26400|60,0:24327,24406|61,0:22402,22481|62,0:24140,24219|64,0:21470,21549|65,0:23138,23217|66,0:21845,21924|67,0:23362,23441|68,0:23600,23679|69,0:23511,23590|71,0:17157,17236|72,0:30779,30858|76,0:617,641,705,892|91,0:417|134,0:556,660,671|152,0:3462|162,0:620|175,0:2160,2207|178,0:1929|179,0:2486,3257,4471,4891|187,0:1958,9251|188,0:806,4464,5171,6024,8304|190,0:3435|191,0:1691,10184"/><wd nm="key1" rd="119,0:3982|123,0:785|125,0:758|126,0:1365,1826,4961,5475"/><wd nm="key2" rd="119,0:3996|123,0:799|125,0:772|126,0:1379,1840,4975,5489"/><wd nm="key:value" rd="76,0:786,1379"/><wd nm="keys" rd="50,0:26669|51,0:25045,25304|52,0:28871,29130|53,0:25647,25906|54,0:28427,28686|55,0:23682,23941|56,0:21472,21731|57,0:24167|58,0:31671|59,0:26559|60,0:24575,24834|61,0:22650,22909|62,0:24388,24647|64,0:21718,21977|65,0:23386,23645|66,0:22093,22352|67,0:23610,23869|68,0:23848,24107|69,0:23748|71,0:17405,17664|72,0:31027,31286"/><wd nm="keyword" rd="201,0:583"/><wd nm="kflashversion" rd="126,0:3303,3609"/><wd nm="kfn" rd="188,0:6241"/><wd nm="kfnaftercloning" rd="168,0:18910"/><wd nm="kfunction" rd="112,0:455,693|131,0:10851,11089"/><wd nm="kground" rd="0,0:92,151,236,498,2553,2865,2960,3326,3368,3421,3726,3769,3988,4465,4531,4578,4746,4807,4903,5178,5220,5315,5531,5649,6140,6158,6483|1,0:3942,4009,4173,4591,4646,4675,4713|2,0:86,223,260,276,308,406,452,626,661,750,833,924,1041,2627|15,0:1687,1877|16,128:33,78,90,117,151,172,330,527,1275,1315,1512,2127,2205,2365,4582,4874,4926,5222,5506,5553,5721,5782,5879,6188,6283,6499,6618,7079,7425,8063,8512,8968,9759,9805,9853,10495,10586,10625,10704,10940,11160,11211,11264,11324,11568,11826,11991|17,0:299|19,0:169,204|21,0:1747,6798,7622|23,0:4561|26,0:2327,3709|27,0:79,215,252,268,300,395,441,615,649,737,820,911,1027,2598|28,0:3648,4928,4976,5327|33,0:3398|34,0:1365|50,0:1673,1684,1711,5311,7023,15642,15658,15977,16072,16306,16341,16490,16633,16808,16855,17081,17280,17726,17823,17895,18025,18126,18228,18299,25329,25384,25902,33482,33659|51,0:5055,5066,5093,8734,12647,15369,15385,15704,15799,16033,16068,16217,16360,16535,16582,16808,17007,17453,17550,17622,17752,17853,17955,18026,21500,21704,23907,23962,24480,34893,35070|52,0:3794,3805,3832,7462,9369,16739,17184,17652,17668,18281,18376,18610,18645,18794,18937,19112,19159,19385,19584,20030,20127,20199,20329,20430,20532,20603,23719,24300,27511,27566,28084,35637,35814,45951,46668,48338,48572|53,0:3342,3353,3380,6744,8467,15655,16100,16568,16584,17197,17292,17526,17561,17710,17853,18028,18075,18301,18500,18946,19043,19115,19245,19346,19448,19519,24287,24342,24860,32405,32582|54,0:3718,3729,3756,7391,9298,17174,17619,18087,18103,18716,18811,19045,19080,19229,19372,19547,19594,19820,20019,20465,20562,20634,20764,20865,20967,21038,23693,23897,27067,27122,27640,35185,35362,47042,47299,50468,50532|55,0:5258,5269,5296,8742,10465,15352,15864,15880,16507,16602,16836,16871,17020,17163,17338,17385,17611,17810,18256,18353,18425,18562,18668,18770,18846,22322,22532,23050,29257,29441,43130,43384|56,0:2278,2289,2316,5568,7290,12443,12459,12778,12873,13107,13142,13290,13433,13608,13655,13881,14080,14526,14623,14695,14825,14926,15028,15099,20109,20164,20682,28231,28408|57,0:2444,2455,2482,6215,8126,13330,13346,13665,13760,13994,14028,14176,14319,14494,14541,14767,14966,15412,15509,15581,15711,15812,15914,15985,19439,19643,22824,22879,23397,30983,31160,41441,41698,44868,45030|58,0:3814,3825,3852,7786,9498,17000,17016,17335,17430,17664,17698,17846,17989,18164,18211,18437,18636,19082,19179,19251,19381,19482,19584,19655,25492,25696,30328,30383,30901,45861,46038,55982,56239|59,0:2898,2909,2936,6597,8680,12904,12920,13239,13334,13568,13603,13752,13895,14070,14117,14343,14542,14988,15085,15157,15287,15388,15490,15561,23891,24068,25219,25274,25792|60,0:3239,3250,3277,6906,8827,13284,13300,13913,14008,14242,14276,14424,14567,14742,14789,15015,15214,15660,15757,15829,15959,16060,16162,16233,19510,20091,23212,23267,23785,31321,31498,41136,41851,42978,43212|61,0:2987,2998,3025,6387,8109,12718,12734,13347,13442,13676,13711,13860,14003,14178,14225,14451,14650,15096,15193,15265,15395,15496,15598,15669,21287,21342,21860,29345,29522|62,0:3253,3264,3291,6927,8839,13807,13823,14436,14531,14765,14799,14947,15090,15265,15312,15538,15737,16183,16280,16352,16482,16583,16685,16756,19627,19831,23025,23080,23598,31143,31320,42365,42622,45417,45481|63,0:2685,2696,2723,6112,7834,14041,14057,14167,14262,14496,14531,14680,14823,14998,15045,15271,15470,15916,16013,16085,16215,16316,16418,16489,19710,19914,28802,28979,33492,33651|64,0:2672,2683,2710,6184,7906,11874,11890,12503,12598,12832,12867,13016,13159,13334,13381,13607,13806,14252,14349,14421,14551,14652,14754,14825,20358,20413,20930,28476,28653|65,0:2933,2944,2971,6710,8630,12956,12972,13585,13680,13914,13948,14096,14239,14414,14461,14687,14886,15332,15429,15501,15631,15732,15834,15905,18831,19035,22023,22078,22596,30141,30318,41029,41286,44701,44863|66,0:2762,2773,2800,6061,7982,12056,12072,12685,12780,13014,13048,13196,13339,13514,13561,13787,13986,14432,14529,14601,14731,14832,14934,15005,17939,18143,20732,20787,21305,28856,29033,46211,46468,49273,49337|67,0:2947,2958,2985,6622,8344,13289,13305,13918,14013,14247,14282,14431,14574,14749,14796,15022,15221,15667,15764,15836,15966,16067,16169,16240,18846,19050,22247,22302,22820,30363,30540,41222,41479,44441,44603|68,0:2974,2985,3012,6646,8368,12803,12819,13432,13527,13761,13795,13943,14086,14261,14308,14534,14733,15179,15276,15348,15478,15579,15681,15752,19162,19366,22486,22541,23059,30602,30779,41704,41961,44854,45016|69,0:2464,2475,2502,6113,8025,13193,13209,13822,13917,14151,14186,14335,14478,14653,14700,14926,15125,15571,15668,15740,15870,15971,16073,16149,19023,19227,22409,22464,22982,30556,30733,41201,41458,44655,44817|70,0:3766,3777,3804,5614,8008,8024,8325,8420,8654,8688,8836,8979,9154,9201,9427,9626,10072,10169,10241,17482,17659|71,0:2046,2057,2084,4097,8646,8662,8981,9076,9310,9344,9492,9635,9810,9857,10083,10282,10728,10825,10897,14278,14482,16042,16097,16615,24159,24336,30629,30886,33251,33413|72,0:4204,4215,4242,7955,9664,16441,17108,17124,17737,17832,18066,18101,18250,18393,18568,18615,18841,19040,19486,19583,19655,19785,19886,19988,20059,24569,24773,29667,29722,30240,38993,39170,47432,47689|73,0:2147,2158,2185,5694,7416,12308,12324,12434,12529,12763,12798,12947,13090,13265,13312,13538,13737,14183,14280,14352,14482,14583,14685,14756,17724,17928,26824,27001,33896,34200|74,0:2178,2189,2216,5738,7461,11833,11849,11959,12054,12288,12323,12472,12615,12790,12837,13063,13262,13708,13805,13877,14007,14108,14210,14281,18329,18533,27341,27518,34701,35005|75,0:1211,1222,1249,4602,6324,11096,11112,11222,11317,11551,11585,11734,11877,12052,12099,12325,12524,12970,13067,13139,13269,13370,13472,13543,25628,25805|81,0:1156|82,0:1424|87,0:888,911|88,0:1385|95,0:13999|106,0:3272|109,0:970|111,0:11175|115,0:7632,9075|116,0:1147|117,0:511|118,0:510|123,0:1080,2501,3214,3476,4305,4608|134,0:2166|137,0:4160,4232,4458|148,0:7163|152,0:4778,4911,5055,5089,5221,5241,5335,5372,5525,5688,5717,5767|158,0:1441|168,0:882,909,20892,20943,21023,21621,21671,21756|170,0:3864,9200|173,0:7120,7156,7185,7212,14892,15110,18812|184,0:14146|187,0:3318,3451,3595,3629,3761,3781,3875,3912,4065,4228,4257,4307,10524,10657,10801,10835,10967,10987,11081,11118,11271,11434,11463,11513|188,0:2182,2315,2459,2493,2625,2645,2739,2776,2929,3092,3121,3171|190,0:4749,4882,5026,5060,5192,5212,5306,5343,5496,5659,5688,5738|191,0:3576,3709,3853,3887,4019,4039,4133,4170,4323,4486,4515,4565|205,0:1581|210,0:1497|212,0:805,2966,3571|213,0:852|214,0:5039,5050,5077|215,0:1001|216,0:785,815,1766"/></pk>