<?xml version="1.0" encoding="UTF-8" standalone="no"?>
<pk><wd nm="egendallowdrag" rd="50,0:25644|51,0:24222|52,0:27826|53,0:24602|54,0:27382|55,0:22792|56,0:20424|57,0:23139|58,0:30643|59,0:25534|60,0:23527|61,0:21602|62,0:23340|64,0:20673|65,0:22338|66,0:21047|67,0:22562|68,0:22801|69,0:22724|71,0:16357|72,0:29982"/><wd nm="egendbgalpha" rd="28,0:4956|50,0:25357|51,0:23935|52,0:27539|53,0:24315|54,0:27095|55,0:22505|56,0:20137|57,0:22852|58,0:30356|59,0:25247|60,0:23240|61,0:21315|62,0:23053|64,0:20386|65,0:22051|66,0:20760|67,0:22275|68,0:22514|69,0:22437|71,0:16070|72,0:29695"/><wd nm="egendbgcolor" rd="28,0:4906|50,0:25301|51,0:23879|52,0:27483|53,0:24259|54,0:27039|55,0:22294|56,0:20081|57,0:22796|58,0:30300|59,0:25191|60,0:23184|61,0:21259|62,0:22997|64,0:20330|65,0:21995|66,0:20704|67,0:22219|68,0:22458|69,0:22381|71,0:16014|72,0:29639"/><wd nm="egendborderalpha" rd="28,0:5113|50,0:25534|51,0:24112|52,0:27716|53,0:24492|54,0:27272|55,0:22682|56,0:20314|57,0:23029|58,0:30533|59,0:25424|60,0:23417|61,0:21492|62,0:23230|64,0:20563|65,0:22228|66,0:20937|67,0:22452|68,0:22691|69,0:22614|71,0:16247|72,0:29872|197,0:1391,2799"/><wd nm="egendbordercolor" rd="28,0:5004|50,0:25412|51,0:23990|52,0:27594|53,0:24370|54,0:27150|55,0:22560|56,0:20192|57,0:22907|58,0:30411|59,0:25302|60,0:23295|61,0:21370|62,0:23108|64,0:20441|65,0:22106|66,0:20815|67,0:22330|68,0:22569|69,0:22492|71,0:16125|72,0:29750|197,0:1367,2773"/><wd nm="egendborderthickness" rd="28,0:5054|50,0:25468|51,0:24046|52,0:27650|53,0:24426|54,0:27206|55,0:22616|56,0:20248|57,0:22963|58,0:30467|59,0:25358|60,0:23351|61,0:21426|62,0:23164|64,0:20497|65,0:22162|66,0:20871|67,0:22386|68,0:22625|69,0:22548|71,0:16181|72,0:29806"/><wd nm="egendcaption" rd="50,0:24711|51,0:23667|52,0:27271|53,0:24047|54,0:26827|55,0:22082|56,0:19869|57,0:22462|58,0:30098|59,0:24858|60,0:22972|61,0:21047|62,0:22785|64,0:20118|65,0:21783|66,0:20492|67,0:22007|68,0:22246|69,0:22047|71,0:15802|72,0:29427"/><wd nm="egendfont" rd="28,0:5792,5900,5977,6067"/><wd nm="egendicon" rd="59,0:27347|159,0:849,1049"/><wd nm="egendiconscale" rd="28,0:3114,3202|50,0:24789|51,0:23745|52,0:27349|53,0:24125|54,0:26905|55,0:22160|56,0:19947|57,0:22540|58,0:30176|59,0:24936|60,0:23050|61,0:21125|62,0:22863|64,0:20196|65,0:21861|66,0:20570|67,0:22085|68,0:22324|69,0:22125|71,0:15880|72,0:29505|168,0:20329,20377"/><wd nm="egenditemclicked" rd="172,0:15595"/><wd nm="egendmarkercircle" rd="51,0:25225|52,0:29051|53,0:25827|54,0:28607|55,0:23862|56,0:21652|60,0:24755|61,0:22830|62,0:24568|64,0:21898|65,0:23566|66,0:22273|67,0:23790|68,0:24028|71,0:17585|72,0:31207|168,0:20635"/><wd nm="egendnumcolumn" rd="69,0:23622"/><wd nm="egendnumcolumns" rd="28,0:4142|50,0:26542|51,0:24908|52,0:28734|53,0:25510|54,0:28290|55,0:23545|56,0:21335|57,0:24040|58,0:31544|59,0:26432|60,0:24438|61,0:22513|62,0:24251|64,0:21581|65,0:23249|66,0:21956|67,0:23473|68,0:23711|71,0:17268|72,0:30890"/><wd nm="egendpadding" rd="50,0:36907|51,0:37526|52,0:38754|53,0:35817|54,0:38312|55,0:30281|56,0:31644|57,0:34111|58,0:48896|59,0:22570|60,0:34448|61,0:32781|62,0:34272|64,0:31038|65,0:33269|66,0:31588|67,0:33491|68,0:33729|69,0:33685|71,0:26450|72,0:42025"/><wd nm="egendpointerheight" rd="59,0:26807|159,0:744"/><wd nm="egendpointers" rd="59,0:26887|156,0:5017,6551,6711,6839"/><wd nm="egendpointerwidth" rd="59,0:26729|159,0:642"/><wd nm="egendposition" rd="28,0:2906,2934|50,0:25170|51,0:23536|52,0:27140|53,0:23916|54,0:26696|55,0:21951|56,0:19738|57,0:22664|58,0:29967|59,0:25060|60,0:22841|61,0:20916|62,0:22654|64,0:19987|65,0:21652|66,0:20361|67,0:21876|68,0:22115|69,0:22249|71,0:15671|72,0:29296"/><wd nm="egends" rd="14,0:980|21,0:951|59,0:11591,39035|155,0:2789|159,0:217,876|160,0:8769,8797|162,0:951,6855,6963|170,0:3139,5429,5521"/><wd nm="egendscalealpha" rd="159,0:433"/><wd nm="egendscalelinealpha" rd="59,0:27169"/><wd nm="egendscalelinecolor" rd="59,0:27090|159,0:325"/><wd nm="egendscalelinethickness" rd="59,0:27260|159,0:531"/><wd nm="egendscrollbarcolor" rd="28,0:3678,5357|50,0:25932|51,0:24510|52,0:28114|53,0:24890|54,0:27670|55,0:23080|56,0:20712|57,0:23427|58,0:30931|59,0:25822|60,0:23815|61,0:21890|62,0:23628|64,0:20960|65,0:22626|66,0:21335|67,0:22850|68,0:23089|69,0:23012|71,0:16645|72,0:30270"/><wd nm="egendscrollbgcolor" rd="28,0:3588,5208|50,0:25777|51,0:24355|52,0:27959|53,0:24735|54,0:27515|55,0:22925|56,0:20557|57,0:23272|58,0:30776|59,0:25667|60,0:23660|61,0:21735|62,0:23473|64,0:20806|65,0:22471|66,0:21180|67,0:22695|68,0:22934|69,0:22857|71,0:16490|72,0:30115"/><wd nm="egendscrollbtncolor" rd="28,0:3762,5500|50,0:26081|51,0:24659|52,0:28263|53,0:25039|54,0:27819|55,0:22350|56,0:20861|57,0:23576|58,0:31080|59,0:25971|60,0:23964|61,0:22039|62,0:23777|64,0:21108|65,0:22775|66,0:21484|67,0:22999|68,0:23237|69,0:23161|71,0:16794|72,0:30419"/><wd nm="egendshadow" rd="28,0:5161|50,0:25589|51,0:24167|52,0:27771|53,0:24547|54,0:27327|55,0:22737|56,0:20369|57,0:23084|58,0:30588|59,0:25479|60,0:23472|61,0:21547|62,0:23285|64,0:20618|65,0:22283|66,0:20992|67,0:22507|68,0:22746|69,0:22669|71,0:16302|72,0:29927"/><wd nm="egendsnaprange" rd="59,0:27004|156,0:5154,5500,5861,6120"/><wd nm="egendsubiconscale" rd="50,0:24913"/><wd nm="eger" rd="50,0:26574|51,0:24950|52,0:28776|53,0:25552|54,0:28332|55,0:23587|56,0:21377|57,0:24072|58,0:31576|59,0:26464|60,0:24480|61,0:22555|62,0:24293|64,0:21623|65,0:23291|66,0:21998|67,0:23515|68,0:23753|69,0:23653|71,0:17310|72,0:30932|76,0:1084|209,0:8152"/><wd nm="egible" rd="6,0:2487|8,0:685|31,0:2487,5670|168,0:31752"/><wd nm="egin" rd="40,0:72|108,0:3781,4737|109,0:4036|111,0:5276,5880,7119,8134|131,0:8479|148,0:2459|183,0:9019|194,0:68|195,0:60|218,0:68"/><wd nm="eginexport" rd="108,0:2001|111,0:639,5553,5591,5805,6224|126,0:2160,5855,7197"/><wd nm="eginexportall" rd="126,0:7345"/><wd nm="eginning" rd="9,0:1040,4298|25,0:6102|78,0:7384|144,0:6054|145,0:3104|152,0:9800|154,0:3107|156,0:1480|168,0:17413|187,0:592,7225,7286|188,0:4835|190,0:544,9354|209,0:8996"/><wd nm="egins" rd="14,0:5068|32,0:1980|132,0:7019"/><wd nm="egion" rd="9,0:1215|78,0:7557"/><wd nm="egionwisesales" rd="149,0:3284,5886"/><wd nm="egister" rd="146,0:6262|170,0:8293|182,0:3177|183,0:1443,8643|185,0:1807"/><wd nm="egistered" rd="81,0:1355"/><wd nm="egisters" rd="173,0:4990"/><wd nm="egisterwithjs" rd="144,0:7448,7512|146,0:1389,1544,2400,3648,4004,6238|173,0:6890|220,0:3480|221,0:3438"/><wd nm="egistration" rd="173,0:4823|181,0:445,1312,1351|182,0:806,3058"/><wd nm="eglected" rd="63,0:12314"/><wd nm="egment" rd="197,0:434"/><wd nm="egmentation" rd="25,0:4371"/><wd nm="egmented" rd="25,0:4318"/><wd nm="egmenting" rd="25,0:4234"/><wd nm="egments" rd="197,0:4013|200,0:223|201,0:350"/><wd nm="egorical" rd="25,0:4272,4331"/><wd nm="egories" rd="3,0:2158,2215,2427|25,0:748,911,1209,1477,1524,1743,1822,2002,2040,2092,5611,5701,5799,7533,7565,7720,7863,8061,8894,9361,9451,9530|28,0:935,1186,1954|40,0:320,394,845|46,0:1137,1211,1479|49,0:977,1068,5887,10338|50,0:293,607,681,1148,38168,38190,38329,38371,40196,40360,49028|51,0:293,710,753,2740,37912,37934,38018|52,0:335,833,1000,2360,40015,40037,40173,40215,42117,42281,47681|53,0:339,786,953,2185,37078,37100,37217,37259,39122,39286,43587|54,0:335,829,996,2284,39573,39595,39712,39754,41563,41727,47735|55,0:307,33023,33045,33152|56,0:278,683,829,1579,32904,32926,33043,33085,34690,34854|57,0:289,660,786,1460,35371,35393,35532,35574,37206,37370|58,0:306,773,1062,2307,15772,15983,16019,16110,16220,50157,50179,50313,50359,50450|59,0:38110|60,0:307,668,919,1829,35708,35730,35869,35911,37804,37968,42608|61,0:311,684,935,1846,34041,34063,34202,34244,36134,36298,39885|62,0:311,678,929,1839,35533,35555,35694,35736,37628,37792,43083|64,0:303,666,917,1776,33172,33194,33333,33375,35260,35424,38981|65,0:299,650,901,1760,34530,34552,34690,34732,36623,36787,42061|66,0:301,705,854,1655,32849,32871,33010,33052,34886,35050,46940|67,0:308,674,925,1784,34752,34774,34913,34955,36854,37018,42016|68,0:320,698,949,1808,34990,35012,35151,35193,37086,37250,42432|69,0:313,679,930,1523,34946,34968,35103,35145,36961,37125,42229|70,0:19342|71,0:275,506,772,1188,26546,26568,26707,26749,31349|72,0:324,845,1376,2585,14852,15063,15099,15190,15300,43286,43308,43425,43457,43548|74,0:31837,35548,35712|76,0:2340,2424,2896,3519,3552|82,0:2540,2692|83,0:2074,2185,3510|84,0:1009,1120,1819,3023,3190,4422|102,0:397,561,1066,2065|104,0:407,539,1029,2044|106,0:597,735,1634,3134|107,0:1120,1266,2059,2969,3095,3546,4117,4564,5427|136,0:3187,3312,3924|154,0:104,3350|168,0:24403,24694,25772,25917,25946,25986,26063,26206,26404,27254,27383,27584|183,0:4841,4889,5000,12087,12135,12246|194,0:320,411,720|195,0:361,452,798|196,0:940,1046,1590,2289,2401,2972|197,0:1445,1709,2859|198,0:522,666,1031,1838|199,0:1061,1210,2041|203,0:317,452,720,1193|204,0:188,728,918,1608|205,0:2748,3215|206,0:1666,2134,3903|207,0:956,1487,2697"/><wd nm="egorized" rd="172,0:247|200,0:249"/><wd nm="egory" rd="3,0:2168,2191,2441|10,0:2579,3457|14,0:95|25,0:758,772,802,832,862,892,1222,1597,5777,5862,7659,7873,7935,7997,8869,9283|28,0:945,965,985,1005,1025,1045,1065,1085,1105,1125,1145,1165,1967|34,0:374,540|40,0:330,351,372,858,1420|46,0:1147,1168,1189,1492|49,0:987,1013,1039,5900,10351,10485,10594|50,0:311,617,638,659,1161,38308,38694,38715,38816,38940,38994,39282,39687,40171,40206,40230,40254,40311,40335,48936,49703|51,0:311,720,2753,38442,38562,38628,38683,38758,38866,38980,39001,39081,39276,39532,39681,40086,41729|52,0:353,843,873,903,935,967,2373,36151,40152,40538,40559,40657,40781,40835,41123,41526,42092,42127,42151,42175,42232,42256,47589,49463|53,0:357,796,826,856,888,920,2198,32897,37196,37582,37603,37701,37825,37879,38167,38572,39097,39132,39156,39180,39237,39261,43495,45728|54,0:353,839,869,899,931,963,2297,35699,39691,40077,40098,40199,40323,40377,40665,41068,41538,41573,41597,41621,41678,41702,47643,49211|55,0:325,33533,33653,33719,33774,33849,33957,34071,34092,34172,34360,34648,34797,35198|56,0:296,693,720,746,771,801,1592,28723,33022,33408,33429,33510,33798,34203,34665,34700,34724,34748,34805,34829,40284|57,0:307,670,692,719,741,763,1473,31497,35511,35898,35919,36000,36287,36690,37181,37216,37240,37264,37321,37345,43508|58,0:324,834,879,924,969,1014,2369,46375,50292,50842,50962,51028,51083,51158,51266,51380,51401,51482,51677,51968,58829|59,0:11627,11671,36024|60,0:325,678,698,718,738,758,778,798,818,838,858,878,898,1842,31835,35848,36234,36255,36356,36480,36534,36822,37225,37779,37814,37838,37862,37919,37943,42520,44100|61,0:329,694,714,734,754,774,794,814,834,854,874,894,914,1859,29859,34181,34567,34588,34689,34813,34867,35155,35560,36109,36144,36168,36192,36249,36273,39793,41674|62,0:329,688,708,728,748,768,788,808,828,848,868,888,908,1852,31657,35673,36059,36080,36181,36305,36359,36647,37050,37603,37638,37662,37686,37743,37767,42991,44148|64,0:321,676,696,716,736,756,776,796,816,836,856,876,896,1789,28990,33312,33698,33719,33820,33944,33998,34285,34690,35235,35270,35294,35318,35375,35399,38889,40231|65,0:317,660,680,700,720,740,760,780,800,820,840,860,880,1773,30655,34669,35055,35076,35176,35300,35354,35642,36045,36598,36633,36657,36681,36738,36762,41969,43130|66,0:319,715,738,761,784,807,830,1668,29370,32989,33375,33396,33499,33623,33677,33965,34368,34861,34896,34920,34944,35001,35025,46848,48005|67,0:326,684,704,724,744,764,784,804,824,844,864,884,904,1797,30877,34892,35278,35299,35400,35524,35578,35866,36269,36829,36864,36888,36912,36969,36993,41928,43071|68,0:338,708,728,748,768,788,808,828,848,868,888,908,928,1821,31116,35130,35516,35537,35638,35762,35816,36104,36507,37061,37096,37120,37144,37201,37225,42340,43483|69,0:331,689,709,729,749,769,789,809,829,849,869,889,909,1536,31070,35082,35468,35489,35586,35710,35764,36052,36455,36936,36971,36995,37019,37076,37100,42137,43287|70,0:264,622,682,719,746,769,792,818,826,852,881,889,914,936,960,969,977,1014,1068,1143,1168,1215,1223,1284,1345,1408,1458,1518,1581,1590,1598,1656,1691,1742,1799,1852,1860,1895,1953,2014,2023,2032,2349,2409,2447,2476,2553,2602,2673,2728,2912,3225,3261,3432,18960,18981,19048,19298,19580,19992|71,0:293,516,539,562,585,608,631,654,677,700,723,747,1201,24673,26686,27072,27093,27194,27318,27372,27660,28065,31257,32403|72,0:342,906,952,998,1045,1092,1139,1186,1233,1280,1327,2647,39507,43404,43917,44037,44103,44158,44233,44341,44455,44476,44557,44756,45012,49478|74,0:31745,35523,35558,35582,35606,35663,35687|76,0:2350,2370,2403,2909,3587,3643,3693,3742|80,0:4543|82,0:2550,2577,2604,2633,2662|83,0:893,1272,1451,1630,1709,2084,2109,2134,2159,3552|84,0:1019,1044,1069,1094,1832,3033,3063,3093,3125,3157,4435|102,0:408,439,471,501,532,1079,2125|104,0:418,441,469,492,515,1042,2100|106,0:607,632,657,682,707,1647,3185|107,0:1130,1157,1183,1208,1238,2072,2979,3001,3028,3050,3072,3559,4152,4199,4246,4293,4336,4381,4426,4471,4516,5464|136,0:3197,3221,3244,3267,3291,3937,4873|154,128:12,34,56,146,261,275,779,2033,3215,3250,3409,3465,4200,4268,4292,4388,5052|155,0:3099|158,0:1782,2767,3954,4383,5084,5511|160,0:399,457|161,0:913,952|162,0:4152,4375,5657,6792|168,0:24704,25782,25996,26216,26278,26340,27233,27335,27752|170,0:2197|183,0:4859,4899,4924,4949,4974,12105,12145,12170,12195,12220|194,0:330,350,370,390,733,1280|195,0:371,391,411,431,811,1481|196,0:950,969,988,1007,1026,1603,2300,2320,2340,2360,2380,2985|197,0:1456,1477,1498,1519,1540,1561,1582,1603,1624,1645,1666,1687,2873|198,0:533,555,577,599,621,643,1044,1817|199,0:1071,1094,1117,1140,1163,1186,2054|200,0:425,446,478,512,546,575,612,648,657,695,729,763,792,829,865,874,941,966,1003,1187,1465,1497|201,0:920,980,1017,1044,1067,1090,1116,1124,1150,1179,1187,1212,1234,1258,1267,1275,1312,1366,1441,1466,1513,1521,1582,1643,1706,1756,1816,1879,1888,1896,1954,1989,2040,2097,2150,2158,2193,2251,2312,2321,2330,2643,2707,2748,2779,2869,2925,3007,3065,3264,3603,3642,3829|203,0:328,351,380,405,427,733,1237|204,0:739,772,799,819,846,871,894,1622|205,0:2805,2845,2885,2926,2967,3008,3049,3090,3131,3172|206,0:1701,1744,1787,1830,1873,1916,1959,2002,2045,2088,3940|207,0:1017,1063,1109,1156,1203,1250,1297,1344,1391,1438,2759|212,0:3549"/></pk>