<?xml version="1.0" encoding="UTF-8" standalone="no"?>
<pk><wd nm="bowler" rd="13,0:417,651,1056,1248|34,0:2774,2993"/><wd nm="box" rd="26,0:3732|34,0:435|39,0:0,3227,3774,3847,4148,4430,4631,4699,4756,4824,4900,4983,5070,5146,5233,6068|40,0:0,50,1710|41,0:0,44,223,466,3768|42,0:0,36,687,1206|43,0:0|44,0:0|45,0:0|46,0:0,28,48,317,425,996,1977,2222|47,0:0|48,0:0|50,0:0,36,428,459,499,21383,21464,21539,21615,21708,21803,21902,21995,22090,22189,24345,37148,40136,43381,43462,43537,43613,43706,43801,43900,43993,44088,44187,48733,48883,50565,50646,50721,50797,50890,50985,51084,51177,51272,51371|52,0:38995|53,0:36058|54,0:38553|55,0:32003|56,0:31885|57,0:34351|58,0:49137|59,0:22811|60,0:34688|61,0:33021|62,0:34513|63,0:31853|64,0:32152|65,0:33510|66,0:15274,31829|67,0:33732|68,0:33970|69,0:33926|72,0:42266|73,0:29874|74,0:30392|75,0:28985|83,0:4659,6194,6392,6723|85,0:556,1619,1790|86,0:608,1136,1354,2068,2232|87,0:691|89,0:624|94,0:2775|95,0:72435|109,0:706,741,865,908,1694,2927|111,0:9691,12585|113,0:8426|115,0:5223|117,0:454,534,590,755|118,0:453,533,589,754|121,0:1798,2003|132,0:9294|134,0:2109,2189,2245|143,0:2429|148,0:7923|163,0:1234|165,0:2161,2204,2218|166,0:2855|168,0:13307|170,0:2175,3400,5138|180,0:4821,5684,6802,7727|183,0:4141,6595,6706,6817,6928,7061,7142,7797,7908,8019,8130,8263,8344,8489,12899,13299,13475|184,0:2707,23319,26822|199,0:3300|206,0:6546|212,0:828"/><wd nm="boxalpha" rd="39,0:4635,4760|50,0:21387,21543,43385,43541,50569,50725"/><wd nm="boxandwhisker2d" rd="50,0:77|163,0:1263,1279|166,0:2884,2900"/><wd nm="boxborderalpha" rd="39,0:4987,5150|50,0:21807,22094,43805,44092,50989,51276"/><wd nm="boxbordercolor" rd="39,0:4828,5074|50,0:21619,21906,43617,43904,50801,51088"/><wd nm="boxborderthickness" rd="39,0:4904|50,0:21712,21999,43710,43997,50894,51181"/><wd nm="boxcolor" rd="39,0:4578,4703|40,0:429,451,613,635,939,960,1107,1128,1620,1636|41,0:4422,4444,4691,4712|43,0:996,1018,1212,1234,1486,1507,1684,1705,2298,2320,2608,2629,4273,4307,4724,4756|44,0:1249,1271,1463,1485,1751,1772,1947,1968,2580,2602,2900,2921,3096,3117,4817,4839,5260,5281|45,0:756,778,1086,1107,2545,2567,2866,2887,3614,3636,3953,3974|47,0:1414,1436,1628,1650,1916,1937,2112,2133,2753,2775,3073,3094,4815,4837,5245,5266|48,0:1349,1371,1563,1585,1851,1872,2047,2068,2691,2713,3011,3032,4781,4803,5211,5232|50,0:716,738,902,924,1242,1263,1412,1433,21312,21468,43310,43466,50494,50650|66,0:15235"/><wd nm="boxes" rd="32,0:1820|39,0:302,3292,3724,3947|40,0:1596|42,0:726|50,0:35934,36024|51,0:37430,37516|52,0:38097,38178|53,0:34844,34934|54,0:37646,37736|56,0:30671,30761|57,0:33445,33535|58,0:48796,48886|60,0:33782,33872|61,0:31808,31898|62,0:33606,33696|63,0:31115,31205|64,0:30938,31028|65,0:32603,32693|66,0:5445,30922,31012|67,0:32825,32915|68,0:33063,33153|69,0:33019,33109|72,0:41925,42015|73,0:29136,29226|74,0:29654,29744|75,0:28199,28289|78,0:10338,10372|95,0:7520|148,0:7936|170,0:1285,1337,9963,10109|183,0:3868,4297|184,0:7565|212,0:2992"/><wd nm="bpanel" rd="184,0:27889,29857"/><wd nm="br" rd="13,0:285,298,355,368,424,437,519,532,589,602,658,671,756,953,966,1008,1021,1063,1076,1145,1158,1200,1213,1255,1268|25,0:3270,3305,3411|29,0:1287|34,0:2642,2655,2712,2725,2781,2794,2871,2884,2936,2949,3000,3013,3095|50,0:19079,19145|51,0:18512,18578|52,0:21089,21155|53,0:20005,20071|54,0:21524,21590|55,0:19339,19405|56,0:15585,15651|57,0:16765,16831|58,0:20435,20501,22188|59,0:16341,16407|60,0:16719,16785|61,0:16154,16220|62,0:17242,17308|63,0:17477,17543|64,0:15311,15377|65,0:16391,16457|66,0:15561,15627|67,0:16729,16795|68,0:16237,16303|69,0:16642,16708|70,0:10596,10662|71,0:11252,11318|72,0:20545,20611,22418|73,0:15744,15810|74,0:15270,15336|75,0:14532,14598|95,0:18113,18210,18307,18404,42950,43049,43148,43247|168,0:23881|212,0:2210"/><wd nm="brace" rd="76,0:778"/><wd nm="braces" rd="76,0:1427"/><wd nm="brackets" rd="11,0:2147|25,0:27002|76,0:1298"/><wd nm="branches" rd="94,0:2623,3589,3641,4488,4540"/><wd nm="branding" rd="98,0:412"/><wd nm="braries" rd="127,0:1112"/><wd nm="brary" rd="80,0:527,4030|120,0:1998|122,0:2847,2880,3237,3287|131,0:524,2754,2814,3169,3202,3412,3462|132,0:2267|133,0:1240,1390|143,0:1112,1720|153,0:357|164,0:2436|168,0:10809|174,0:1341|181,0:1544|184,0:18490,21505,25189,28913|190,0:6726"/><wd nm="brazil" rd="136,0:3236,3970,4526"/><wd nm="brdatavalues" rd="59,0:5759,5772|158,0:2486,3386"/><wd nm="break" rd="13,0:713|24,0:136|34,0:3052"/><wd nm="breakdown" rd="149,0:381"/><wd nm="breaking" rd="8,0:228|31,0:5213|168,0:31295"/><wd nm="breaks" rd="13,0:166,861|170,0:5921|193,0:212"/><wd nm="breviated" rd="14,0:3316"/><wd nm="brevity" rd="132,0:3048"/><wd nm="brew" rd="9,0:382,405|78,0:7744,7767"/><wd nm="bri" rd="56,0:1255,2066|57,0:1188,1955"/><wd nm="bridge" rd="76,0:514|115,0:5974|132,0:4934"/><wd nm="brief" rd="14,0:4638|26,0:3309|95,0:68747|168,0:21221|184,0:17256,19933,23409,27253|212,0:256"/><wd nm="briefly" rd="143,0:515|216,0:1575"/><wd nm="brightest" rd="156,0:3611"/><wd nm="bring" rd="96,0:603|97,0:600|165,0:2190"/><wd nm="brlabel" rd="59,0:36589,37388|154,0:4100|158,0:1054,3665,4207,4589,5314,5696"/><wd nm="brlabelfont" rd="158,0:2075,2507,3029,3406"/><wd nm="broad" rd="172,0:265"/><wd nm="broader" rd="178,0:884"/><wd nm="broadly" rd="100,0:494|142,0:308"/><wd nm="broken" rd="8,0:1780|31,0:6768|52,0:8634|54,0:8563|57,0:7401|60,0:8092|62,0:8104|65,0:7895|66,0:7246|69,0:7299|78,0:7972|168,0:33085|208,0:1772"/><wd nm="browse" rd="165,0:2257,2275"/><wd nm="browser" rd="7,0:1349|12,0:704|78,0:1109,5976,8542,8682|79,0:770,3095|80,0:1045,1998,2034|81,0:2500,5398|93,0:694,758|98,0:1002,1070|111,0:1065|112,0:1212|113,0:4140|115,0:2406,5198|119,0:297,3405|120,0:720,806|121,0:980,1295,1429,2618,2647|124,0:2525,2822|126,0:3416|127,0:175,597,2926,2969,3078|130,0:335,509,646,1413|131,0:157|132,0:1678,2735|133,0:1530,1615,3105|138,0:1349|139,0:2390,2759,3025|142,0:956|143,0:1436|144,0:1970,3440,5147,7082,10466,10975|145,0:1109,1768,5248,6404,6913|146,0:721,2437,2752|152,0:6224|153,0:1332,2340,2512,4764|167,0:447|168,0:1955,3488,6373,7215,12091|169,0:616|170,0:1390,10537,10789|172,0:7388|173,0:7681|181,0:3229,3311,3497,3680,3787,3864|182,0:557,3130|187,0:4777,11981|188,0:3639|190,0:6208|191,0:5035|212,0:1248"/><wd nm="browser&apos;s" rd="7,0:1611,1633|139,0:3040|168,0:6388,8191|185,0:1362|186,0:768"/><wd nm="browsers" rd="78,0:301,5346|80,0:1259|94,0:4366|144,0:3822|146,0:704,2639,2883,2966|147,0:1184|150,0:2508|152,0:6755|153,0:228,1379,3758,4851|168,0:7913,11816,12620,14284|173,0:11373,12191,13312,21657,22237,22957|174,0:479,573|185,0:998,3695|186,128:24,58,272,374,1386,5065|190,0:6984|191,0:7971"/><wd nm="browser’s" rd="78,0:945|80,0:840"/><wd nm="brtype" rd="59,0:8902,37449|158,0:3726,3904,4314,5122,5547"/><wd nm="bruary" rd="14,0:3502,4052|40,0:157,605,1098,1473|43,0:1204,1675|44,0:1455,1938,3087|47,0:1620,2103|48,0:1555,2038|50,0:894,1403|95,0:18934,19470,25012,25550,31097,31633,37172,37708,43845,44421,50209,50787,56580,57156,62941,63517|150,0:429,1368,3130,3687|168,0:16045"/><wd nm="bs" rd="81,0:3774|146,0:1225,3500"/><wd nm="bs:true" rd="184,0:27931,29899"/><wd nm="bscription" rd="70,0:1547,3140|201,0:1845,3510"/><wd nm="bsent" rd="9,0:1682"/><wd nm="bsequent" rd="75,0:17063|95,0:14176|184,0:27744"/><wd nm="bserve" rd="46,0:349"/><wd nm="bserved" rd="25,0:25424"/><wd nm="bset" rd="207,0:122"/><wd nm="bsite" rd="39,0:1817,1915,2593,2745|40,0:126,287,812,1504|41,0:4347,4613|43,0:466,558,924,1411,2226,2533,4182,4631|44,0:608,713,1162,1662,2493,2811,4738,5178|45,0:684,1011,2487,2804,3537,3873|46,0:1104,1446|47,0:708,813,1327,1827,2666,2984,4723,5151|48,0:683,788,1262,1762,2604,2922,4689,5117|50,0:557,1099|60,0:573,948,1201,1737,2020,2216|61,0:589,964,1217,1754,2037,2233|62,0:583,958,1211,1747,2030,2226|78,0:4716|114,0:804|126,0:7813|137,0:3455,3742|165,0:475|187,0:12132|188,0:3788"/><wd nm="bsolute" rd="7,0:109,676|16,0:8177,8322|25,0:25347|29,0:1005|41,0:2254|52,0:16207|53,0:15123|54,0:16642|55,0:14820|63,0:11960,12450|72,0:15837|78,0:2177,2382|82,0:991|88,0:953|98,0:880,1088,1314,1635|131,0:5635,5776|173,0:11337,12155,13171|193,0:2813|205,0:1148"/><wd nm="bsolutely" rd="78,0:492|137,0:1214|144,0:4052|147,0:1375|150,0:2735|153,0:1570,3949|173,0:1548,11580,12399,13525"/><wd nm="bsp" rd="183,0:6670,6684,6690,6781,6795,6801,6892,6906,6912,7003,7017,7023,7120,7126,7235,7241,7872,7886,7892,7983,7997,8003,8094,8108,8114,8205,8219,8225,8322,8328,8436,8442"/><wd nm="btain" rd="77,0:2033|178,0:360"/><wd nm="btained" rd="96,0:5177|97,0:4917"/><wd nm="btn" rd="52,0:15912,16875|53,0:14828,15791|54,0:16347,17310|55,0:675,3103,14525|72,0:16058|82,0:676,1558|83,0:2059|88,0:638,1521,2773|89,0:1571|91,0:1647,4089|205,0:686,1715|206,0:1635,3873"/><wd nm="btnarrowcolor" rd="123,0:4770,5897,6005"/><wd nm="btnbgcolor" rd="52,0:16710,17152|53,0:15626,16068|54,0:17145,17587|55,0:15323|72,0:16412|82,0:1409|88,0:1370|123,0:4558|205,0:1566"/><wd nm="btnbordercolor" rd="52,0:707,737,2242,2271,16647,17085|53,0:729,759,2129,2158,15563,16001|54,0:707,737,2166,2195,17082,17520|55,0:15260|72,0:16349|82,0:1360,2456,2484|84,0:2966,2996,4366,4395|88,0:1322|111,0:11950|115,0:8407|116,0:1922|123,0:4046,4429,4664,4755,5483,5678,5787|205,0:1517"/><wd nm="btnborderthickness" rd="123,0:5802"/><wd nm="btncolor" rd="28,0:3762,5500|50,0:26081|51,0:24659|52,0:28263|53,0:25039|54,0:27819|55,0:22350|56,0:20861|57,0:23576|58,0:31080|59,0:25971|60,0:23964|61,0:22039|62,0:23777|64,0:21108|65,0:22775|66,0:21484|67,0:22999|68,0:23237|69,0:23161|71,0:16794|72,0:30419|111,0:11896|115,0:8353|116,0:1868|123,0:3984,4549,4655,5386,5576,5669"/><wd nm="btndisabledtitle" rd="111,0:12355|115,0:8736|116,0:2251|123,0:2771"/><wd nm="btnfontcolor" rd="111,0:12090|115,0:8547|116,0:2062|123,0:3790"/><wd nm="btnfontface" rd="111,0:12032|115,0:8489|116,0:2004|123,0:3735"/><wd nm="btnfontsize" rd="111,0:12148|115,0:8605|116,0:2120|123,0:3856"/><wd nm="btnheight" rd="111,0:11845|115,0:8302|116,0:1817|123,0:3942,4932"/><wd nm="btnpadding" rd="52,0:16773|53,0:15689|54,0:17208|55,0:15386|72,0:16475"/><wd nm="btnsavealltitle" rd="111,0:12280|123,0:4168"/><wd nm="btnsavetitle" rd="111,0:12216|115,0:8673|116,0:2188|123,0:4116"/><wd nm="btnspacing" rd="52,0:16818|53,0:15734|54,0:17253|72,0:16570"/><wd nm="btntextcolor" rd="52,0:16533|53,0:15449|54,0:16968|55,0:15146|72,0:16522|82,0:1271|88,0:1233|205,0:1428"/></pk>